pytestforge/driver.py
pytestforge/page.py
pytestforge/plugin.py
pytestforge/settings.py
pytestforge/tools.py
pytestforge-1.2.1.dist-info/LICENSE
pytestforge-1.2.1.dist-info/METADATA
pytestforge-1.2.1.dist-info/WHEEL
pytestforge-1.2.1.dist-info/entry_points.txt
pytestforge-1.2.1.dist-info/top_level.txt
pytestforge-1.2.1.dist-info/RECORD
